bart_api_ulloa-0.0.2.dist-info/METADATA
bart_api_ulloa-0.0.2.dist-info/RECORD
bart_api_ulloa-0.0.2.dist-info/WHEEL
bart_api_ulloa-0.0.2.dist-info/top_level.txt
bart_lib/__init__.py
bart_lib/bart.py
