Metadata-Version: 2.1
Name: bart-api-ulloa
Version: 0.0.2
Summary: bart api wrapper in python, now returns data instead of just printing
Home-page: https://github.com/ulloaluis/bart-api-wrapper-python
Author: Luis Ulloa
Author-email: ulloa@stanford.edu
License: UNKNOWN
Platform: UNKNOWN
Classifier: Programming Language :: Python :: 3
Classifier: License :: OSI Approved :: MIT License
Classifier: Operating System :: OS Independent
